<?xml version="1.0" encoding="UTF-8"?>
<!--
  - Spring config for User UI Panels.
  -->
<beans xmlns="http://www.springframework.org/schema/beans"
		xmlns:xsi="http://www.w3.org/2001/XMLSchema-instance"
		xmlns:context="http://www.springframework.org/schema/context"
		xmlns:tx="http://www.springframework.org/schema/tx"
		xmlns:util="http://www.springframework.org/schema/util"
		xsi:schemaLocation="
			http://www.springframework.org/schema/beans http://www.springframework.org/schema/beans/spring-beans-4.0.xsd
			http://www.springframework.org/schema/context http://www.springframework.org/schema/context/spring-context-4.0.xsd
			http://www.springframework.org/schema/tx http://www.springframework.org/schema/tx/spring-tx-4.0.xsd
			http://www.springframework.org/schema/util http://www.springframework.org/schema/util/spring-util-4.0.xsd
			">

		<bean id="userAdminNavigatorPanel" scope="prototype" class="com.rreganjr.requel.user.ui.UserAdminNavigatorPanel">
			<constructor-arg>
				<util:set scope="prototype" value-type="net.sf.echopm.navigation.tree.NavigatorTreeNodeFactory">
					<ref bean="userCollectionNavigatorTreeNodeFactory"/>
					<ref bean="userNavigatorTreeNodeFactory"/>
				</util:set>		
			</constructor-arg>
		</bean>

		<bean id="userEditorPanelFactory" scope="prototype" class="net.sf.echopm.panel.DefaultPanelFactory">
			<constructor-arg index="0"><value type="java.lang.Class">com.rreganjr.requel.user.ui.UserEditorPanel</value></constructor-arg>
			<constructor-arg index="1"><value type="java.lang.Class">com.rreganjr.requel.user.User</value></constructor-arg>
			<constructor-arg index="2"><util:constant static-field="net.sf.echopm.panel.PanelActionType.Editor"/></constructor-arg>
			<constructor-arg index="3">
				<util:list>
					<ref bean="commandHandler"/>
					<ref bean="userCommandFactory"/>
					<ref bean="userRepository"/>
				</util:list>
			</constructor-arg>			
		</bean>
</beans>